setup.py
libforsns/__init__.py
libforsns.egg-info/PKG-INFO
libforsns.egg-info/SOURCES.txt
libforsns.egg-info/dependency_links.txt
libforsns.egg-info/top_level.txt