Metadata-Version: 1.1
Name: libforsns
Version: 0.0.3
Summary: Its a library for subscribing and publishing emails notification through AWS SNS
Home-page: UNKNOWN
Author: Adithiyan
Author-email: itzjustadi29@gmail.com
License: UNKNOWN
Keywords: libforsns
Platform: UNKNOWN
Classifier: Development Status :: 5 - Production/Stable
Classifier: Intended Audience :: Education
Classifier: Operating System :: Microsoft :: Windows :: Windows 10
Classifier: License :: OSI Approved :: MIT License
Classifier: Programming Language :: Python :: 3
